fds/__init__.py
fds/sdk/__init__.py
fds/sdk/FactSetFundamentalsReportBuilder/__init__.py
fds/sdk/FactSetFundamentalsReportBuilder/api_client.py
fds/sdk/FactSetFundamentalsReportBuilder/configuration.py
fds/sdk/FactSetFundamentalsReportBuilder/exceptions.py
fds/sdk/FactSetFundamentalsReportBuilder/model_utils.py
fds/sdk/FactSetFundamentalsReportBuilder/rest.py
fds/sdk/FactSetFundamentalsReportBuilder/api/__init__.py
fds/sdk/FactSetFundamentalsReportBuilder/api/financials_api.py
fds/sdk/FactSetFundamentalsReportBuilder/apis/__init__.py
fds/sdk/FactSetFundamentalsReportBuilder/model/__init__.py
fds/sdk/FactSetFundamentalsReportBuilder/model/error_object.py
fds/sdk/FactSetFundamentalsReportBuilder/model/error_object_links.py
fds/sdk/FactSetFundamentalsReportBuilder/model/error_object_source.py
fds/sdk/FactSetFundamentalsReportBuilder/model/error_response.py
fds/sdk/FactSetFundamentalsReportBuilder/model/meta.py
fds/sdk/FactSetFundamentalsReportBuilder/model/response.py
fds/sdk/FactSetFundamentalsReportBuilder/models/__init__.py
fds.sdk.FactSetFundamentalsReportBuilder-1.0.14.dist-info/LICENSE
fds.sdk.FactSetFundamentalsReportBuilder-1.0.14.dist-info/METADATA
fds.sdk.FactSetFundamentalsReportBuilder-1.0.14.dist-info/WHEEL
fds.sdk.FactSetFundamentalsReportBuilder-1.0.14.dist-info/top_level.txt
fds.sdk.FactSetFundamentalsReportBuilder-1.0.14.dist-info/RECORD
